README.md
setup.py
fastapi_redis/__init__.py
fastapi_redis/redis_cache.py
fastapi_redis/redis_client.py
fastapi_redis/redis_test.py
fastapi_redis.egg-info/PKG-INFO
fastapi_redis.egg-info/SOURCES.txt
fastapi_redis.egg-info/dependency_links.txt
fastapi_redis.egg-info/requires.txt
fastapi_redis.egg-info/top_level.txt