Metadata-Version: 2.1
Name: fastapi-redis
Version: 0.1.11
Summary: Fastapi Redis client with decorator for controllers
Home-page: https://github.com/comtura-ai/fastapi-redis
Author: Comtura
Author-email: info@comtura.ai
License: MIT
Download-URL: https://github.com/comtura-ai/fastapi-redis/archive/refs/heads/main.zip
Keywords: fastapi,redis,cache
Platform: UNKNOWN
